{
    "1": {
      "+hp": 15,
      "act": 10,
      "class": "ALL",
      "image": "item1",
      "rank": "common",
      "type": "eat"
    },
    "2": {
      "+mood": 10,
      "act": 5,
      "class": "ALL",
      "image": "item2",
      "ns_craft": {
        "1": {
          "create": [
            "47"
          ],
          "materials": [
            "2",
            "2",
            "2",
            "2",
            "2",
            "2",
            "2",
            "2",
            "2",
            "2",
            "2",
            "2",
            "2",
            "2",
            "2"
          ]
        }
      },
      "rank": "common",
      "type": "eat"
    },
    "3": {
      "image": "item3",
      "inc_type": "random",
      "incub_time": 12,
      "rank": "rare",
      "time_tag": "h",
      "type": "egg"
    },
    "4": {
      "abilities": {
        "endurance": 100
      },
      "image": "item4",
      "rank": "uncommon",
      "type": "game_ac"
    },
    "5": {
      "act": 25,
      "class": "Carnivore",
      "image": "item5",
      "ns_craft": {
        "1": {
          "create": [
            "12"
          ],
          "materials": [
            "5"
          ]
        }
      },
      "rank": "common",
      "type": "eat"
    },
    "6": {
      "act": 25,
      "class": "Herbivore",
      "image": "item6",
      "ns_craft": {
        "1": {
          "create": [
            "11"
          ],
          "materials": [
            "6"
          ]
        }
      },
      "rank": "common",
      "type": "eat"
    },
    "7": {
      "act": 25,
      "class": "Flying",
      "image": "item7",
      "ns_craft": {
        "1": {
          "create": [
            "80"
          ],
          "materials": [
            "7",
            "7"
          ]
        },
        "2": {
          "create": [
            "13"
          ],
          "materials": [
            "7"
          ]
        }
      },
      "rank": "common",
      "type": "eat"
    },
    "8": {
      "act": 15,
      "class": "Carnivore",
      "image": "item8",
      "ns_craft": {
        "1": {
          "create": [
            "12"
          ],
          "materials": [
            "8",
            "8"
          ]
        }
      },
      "rank": "common",
      "type": "eat"
    },
    "9": {
      "act": 15,
      "class": "Herbivore",
      "image": "item9",
      "ns_craft": {
        "1": {
          "create": [
            "11"
          ],
          "materials": [
            "9",
            "9"
          ]
        },
        "2": {
          "create": [
            "95"
          ],
          "materials": [
            "9"
          ]
        }
      },
      "rank": "common",
      "type": "eat"
    },
    "10": {
      "act": 15,
      "class": "Flying",
      "image": "item10",
      "ns_craft": {
        "1": {
          "create": [
            "13"
          ],
          "materials": [
            "10",
            "10"
          ]
        }
      },
      "rank": "common",
      "type": "eat"
    },
    "11": {
      "act": 20,
      "class": "Herbivore",
      "image": "item11",
      "ns_craft": {
        "1": {
          "create": [
            "9"
          ],
          "materials": [
            "11"
          ]
        },
        "2": {
          "create": [
            "6"
          ],
          "materials": [
            "11",
            "11"
          ]
        }
      },
      "rank": "common",
      "type": "eat"
    },
    "12": {
      "act": 20,
      "class": "Carnivore",
      "image": "item12",
      "ns_craft": {
        "1": {
          "create": [
            "8"
          ],
          "materials": [
            "12"
          ]
        },
        "2": {
          "create": [
            "5"
          ],
          "materials": [
            "12",
            "12"
          ]
        }
      },
      "rank": "common",
      "type": "eat"
    },
    "13": {
      "act": 20,
      "class": "Flying",
      "image": "item13",
      "ns_craft": {
        "1": {
          "create": [
            "7"
          ],
          "materials": [
            "13",
            "13"
          ]
        },
        "2": {
          "create": [
            "10"
          ],
          "materials": [
            "13"
          ]
        }
      },
      "rank": "common",
      "type": "eat"
    },
    "14": {
      "abilities": {
        "endurance": 100
      },
      "image": "item14",
      "rank": "uncommon",
      "type": "journey_ac"
    },
    "15": {
      "abilities": {
        "endurance": 100
      },
      "act": 10,
      "image": "item15",
      "rank": "uncommon",
      "type": "collecting_ac"
    },
    "16": {
      "abilities": {
        "endurance": 100
      },
      "image": "item16",
      "rank": "uncommon",
      "type": "sleep_ac"
    },
    "17": {
      "+hp": 15,
      "act": 1,
      "class": "ALL",
      "image": "item17",
      "rank": "uncommon",
      "type": "eat"
    },
    "18": {
      "+mood": 15,
      "act": 25,
      "class": "ALL",
      "image": "item18",
      "ns_craft": {
        "1": {
          "create": [
            "48"
          ],
          "materials": [
            "18",
            "18",
            "18",
            "18",
            "18",
            "18",
            "18",
            "18",
            "18"
          ]
        }
      },
      "rank": "common",
      "type": "eat"
    },
    "19": {
      "+mood": 20,
      "act": 20,
      "class": "ALL",
      "image": "item19",
      "rank": "common",
      "type": "eat"
    },
    "20": {
      "image": "item20",
      "inc_type": "unc",
      "incub_time": 24,
      "ns_craft": {
        "1": {
          "create": [
            "22"
          ],
          "materials": [
            "20",
            "20",
            "20",
            "20",
            "20",
            "20",
            "20",
            "20",
            "20",
            "20"
          ]
        }
      },
      "rank": "mystical",
      "time_tag": "h",
      "type": "egg"
    },
    "21": {
      "image": "item21",
      "inc_type": "com",
      "incub_time": 30,
      "ns_craft": {
        "1": {
          "create": [
            "20"
          ],
          "materials": [
            "21",
            "21",
            "21",
            "21",
            "21",
            "21",
            "21",
            "21",
            "21",
            "21"
          ]
        }
      },
      "rank": "mystical",
      "time_tag": "m",
      "type": "egg"
    },
    "22": {
      "image": "item22",
      "inc_type": "rar",
      "incub_time": 48,
      "ns_craft": {
        "1": {
          "create": [
            "23"
          ],
          "materials": [
            "22",
            "22",
            "22",
            "22",
            "22",
            "22",
            "22",
            "22",
            "22",
            "22"
          ]
        }
      },
      "rank": "mystical",
      "time_tag": "h",
      "type": "egg"
    },
    "23": {
      "image": "item23",
      "inc_type": "myt",
      "incub_time": 72,
      "ns_craft": {
        "1": {
          "create": [
            "24"
          ],
          "materials": [
            "23",
            "23",
            "23",
            "23",
            "23",
            "23",
            "23",
            "23",
            "23",
            "23"
          ]
        }
      },
      "rank": "mystical",
      "time_tag": "h",
      "type": "egg"
    },
    "24": {
      "image": "item24",
      "inc_type": "leg",
      "incub_time": 110,
      "rank": "legendary",
      "time_tag": "h",
      "type": "egg"
    },
    "25": {
      "image": "item25",
      "rank": "common",
      "type": "material"
    },
    "26": {
      "image": "item26",
      "rank": "common",
      "type": "material"
    },
    "27": {
      "image": "item27",
      "rank": "common",
      "type": "material"
    },
    "28": {
      "image": "item28",
      "rank": "common",
      "type": "material"
    },
    "29": {
      "abilities": {
        "endurance": 100
      },
      "image": "item29",
      "rank": "uncommon",
      "type": "journey_ac"
    },
    "30": {
      "abilities": {
        "uses": 3
      },
      "create": [
        {
          "item": "29",
          "type": "create"
        }
      ],
      "image": "recipe",
      "materials": [
        {
          "item": "26",
          "type": "delete"
        },
        {
          "item": "26",
          "type": "delete"
        },
        {
          "item": "26",
          "type": "delete"
        },
        {
          "item": "26",
          "type": "delete"
        },
        {
          "item": "26",
          "type": "delete"
        }
      ],
      "rank": "rare",
      "type": "recipe"
    },
    "31": {
      "abilities": {
        "endurance": 100
      },
      "image": "item31",
      "rank": "uncommon",
      "type": "collecting_ac"
    },
    "32": {
      "abilities": {
        "uses": 1
      },
      "create": [
        {
          "item": "31",
          "type": "create"
        }
      ],
      "image": "recipe",
      "materials": [
        {
          "item": "27",
          "type": "delete"
        },
        {
          "item": "27",
          "type": "delete"
        },
        {
          "item": "27",
          "type": "delete"
        },
        {
          "item": "27",
          "type": "delete"
        },
        {
          "item": "25",
          "type": "delete"
        },
        {
          "item": "25",
          "type": "delete"
        },
        {
          "item": "25",
          "type": "delete"
        }
      ],
      "rank": "rare",
      "type": "recipe"
    },
    "33": {
      "+hp": 25,
      "-mood": 10,
      "act": 5,
      "class": "ALL",
      "image": "item33",
      "rank": "rare",
      "type": "eat"
    },
    "34": {
      "abilities": {
        "uses": 10
      },
      "create": [
        {
          "item": "33",
          "type": "create"
        }
      ],
      "image": "recipe",
      "materials": [
        {
          "item": "28",
          "type": "delete"
        },
        {
          "item": "28",
          "type": "delete"
        },
        {
          "item": "28",
          "type": "delete"
        },
        {
          "item": "28",
          "type": "delete"
        },
        {
          "item": "28",
          "type": "delete"
        }
      ],
      "rank": "rare",
      "type": "recipe"
    },
    "35": {
      "act": 45,
      "class": "Herbivore",
      "image": "item35",
      "rank": "rare",
      "type": "eat"
    },
    "36": {
      "+energy": 25,
      "act": -30,
      "class": "ALL",
      "image": "item36",
      "rank": "rare",
      "type": "eat"
    },
    "37": {
      "abilities": {
        "uses": 10
      },
      "create": [
        {
          "item": "36",
          "type": "create"
        }
      ],
      "image": "recipe",
      "materials": [
        {
          "item": "35",
          "type": "delete"
        },
        {
          "item": "35",
          "type": "delete"
        },
        {
          "item": "35",
          "type": "delete"
        },
        {
          "item": "35",
          "type": "delete"
        },
        {
          "item": "35",
          "type": "delete"
        }
      ],
      "rank": "rare",
      "type": "recipe"
    },
    "38": {
      "act": 40,
      "class": "Carnivore",
      "image": "item38",
      "rank": "rare",
      "type": "eat"
    },
    "39": {
      "abilities": {
        "uses": 30
      },
      "create": [
        {
          "item": "38",
          "type": "create"
        }
      ],
      "image": "recipe",
      "materials": [
        {
          "act": 10,
          "item": "31",
          "type": "endurance"
        },
        {
          "item": "8",
          "type": "delete"
        },
        {
          "item": "8",
          "type": "delete"
        }
      ],
      "rank": "rare",
      "type": "recipe"
    },
    "40": {
      "act": 70,
      "class": "Herbivore",
      "image": "item40",
      "rank": "rare",
      "type": "eat"
    },
    "41": {
      "abilities": {
        "uses": 40
      },
      "create": [
        {
          "item": "40",
          "type": "create"
        }
      ],
      "image": "recipe",
      "materials": [
        {
          "item": "6",
          "type": "delete"
        },
        {
          "item": "9",
          "type": "delete"
        },
        {
          "item": "11",
          "type": "delete"
        }
      ],
      "rank": "rare",
      "type": "recipe"
    },
    "42": {
      "act": 55,
      "class": "Flying",
      "image": "item42",
      "rank": "rare",
      "type": "eat"
    },
    "43": {
      "abilities": {
        "uses": 40
      },
      "create": [
        {
          "item": "42",
          "type": "create"
        }
      ],
      "image": "recipe",
      "materials": [
        {
          "item": "10",
          "type": "delete"
        },
        {
          "item": "10",
          "type": "delete"
        },
        {
          "item": "10",
          "type": "delete"
        },
        {
          "act": 10,
          "item": "4",
          "type": "endurance"
        }
      ],
      "rank": "rare",
      "type": "recipe"
    },
    "44": {
      "abilities": {
        "endurance": 100
      },
      "image": "item44",
      "rank": "uncommon",
      "type": "game_ac"
    },
    "45": {
      "abilities": {
        "endurance": 100
      },
      "image": "item45",
      "rank": "rare",
      "type": "journey_ac"
    },
    "46": {
      "abilities": {
        "uses": 2
      },
      "create": [
        {
          "item": "45",
          "type": "create"
        }
      ],
      "image": "recipe",
      "materials": [
        {
          "item": "26",
          "type": "delete"
        },
        {
          "item": "26",
          "type": "delete"
        },
        {
          "item": "26",
          "type": "delete"
        },
        {
          "item": "27",
          "type": "delete"
        },
        {
          "item": "27",
          "type": "delete"
        },
        {
          "act": 30,
          "item": "15",
          "type": "endurance"
        }
      ],
      "rank": "rare",
      "type": "recipe"
    },
    "47": {
      "+mood": 10,
      "abilities": {
        "uses": 15
      },
      "act": 6,
      "class": "ALL",
      "image": "item47",
      "rank": "uncommon",
      "type": "eat"
    },
    "48": {
      "+mood": 15,
      "abilities": {
        "uses": 9
      },
      "act": 25,
      "class": "ALL",
      "image": "item48",
      "rank": "uncommon",
      "type": "eat"
    },
    "49": {
      "abilities": {
        "mana": 0
      },
      "image": "item49",
      "rank": "rare",
      "type": "material"
    },
    "50": {
      "+mood": 40,
      "act": 75,
      "class": "ALL",
      "image": "item50",
      "rank": "rare",
      "type": "eat"
    },
    "51": {
      "image": "item51",
      "rank": "common",
      "type": "material"
    },
    "52": {
      "image": "item52",
      "rank": "uncommon",
      "type": "material"
    },
    "53": {
      "abilities": {
        "endurance": 50
      },
      "class": "near",
      "damage": {
        "max": 3,
        "min": 1
      },
      "image": "item53",
      "rank": "uncommon",
      "type": "weapon"
    },
    "54": {
      "abilities": {
        "stack": 1
      },
      "add_damage": 0,
      "add_effects": [],
      "image": "item54",
      "max_stack": 66,
      "rank": "uncommon",
      "type": "ammunition"
    },
    "55": {
      "abilities": {
        "endurance": 70
      },
      "ammunition": [
        "54"
      ],
      "class": "far",
      "damage": {
        "max": 5,
        "min": 1
      },
      "image": "item55",
      "rank": "uncommon",
      "type": "weapon"
    },
    "56": {
      "abilities": {
        "uses": 5
      },
      "create": [
        {
          "item": "50",
          "type": "create"
        }
      ],
      "image": "recipe",
      "materials": [
        {
          "item": "9",
          "type": "delete"
        },
        {
          "item": "9",
          "type": "delete"
        },
        {
          "item": "9",
          "type": "delete"
        },
        {
          "item": "8",
          "type": "delete"
        },
        {
          "item": "8",
          "type": "delete"
        }
      ],
      "rank": "rare",
      "type": "recipe"
    },
    "57": {
      "abilities": {
        "uses": 2
      },
      "create": [
        {
          "item": "53",
          "type": "create"
        }
      ],
      "image": "recipe",
      "materials": [
        {
          "item": "51",
          "type": "delete"
        },
        {
          "item": "51",
          "type": "delete"
        },
        {
          "act": 30,
          "item": "15",
          "type": "endurance"
        },
        {
          "item": "51",
          "type": "delete"
        },
        {
          "item": "51",
          "type": "delete"
        },
        {
          "item": "51",
          "type": "delete"
        }
      ],
      "rank": "rare",
      "type": "recipe"
    },
    "58": {
      "abilities": {
        "uses": 2
      },
      "create": [
        {
          "item": "55",
          "type": "create"
        }
      ],
      "image": "recipe",
      "materials": [
        {
          "item": "51",
          "type": "delete"
        },
        {
          "item": "51",
          "type": "delete"
        },
        {
          "act": 30,
          "item": "15",
          "type": "endurance"
        },
        {
          "item": "51",
          "type": "delete"
        },
        {
          "item": "51",
          "type": "delete"
        },
        {
          "item": "51",
          "type": "delete"
        }
      ],
      "rank": "rare",
      "type": "recipe"
    },
    "59": {
      "abilities": {
        "uses": 11
      },
      "create": [
        {
          "abilities": {
            "stack": 3
          },
          "item": "54",
          "type": "create"
        }
      ],
      "image": "recipe",
      "materials": [
        {
          "item": "51",
          "type": "delete"
        },
        {
          "act": 10,
          "item": "15",
          "type": "endurance"
        }
      ],
      "rank": "rare",
      "type": "recipe"
    },
    "60": {
      "capacity": 10,
      "image": "item45",
      "rank": "rare",
      "type": "backpack"
    },
    "61": {
      "abilities": {
        "uses": 2
      },
      "create": [
        {
          "item": "60",
          "type": "create"
        }
      ],
      "image": "recipe",
      "materials": [
        {
          "item": "26",
          "type": "delete"
        },
        {
          "item": "26",
          "type": "delete"
        },
        {
          "item": "26",
          "type": "delete"
        },
        {
          "item": "26",
          "type": "delete"
        },
        {
          "item": "26",
          "type": "delete"
        },
        {
          "item": "26",
          "type": "delete"
        },
        {
          "item": "26",
          "type": "delete"
        },
        {
          "item": "26",
          "type": "delete"
        },
        {
          "item": "26",
          "type": "delete"
        },
        {
          "item": "26",
          "type": "delete"
        },
        {
          "item": "26",
          "type": "delete"
        },
        {
          "item": "26",
          "type": "delete"
        },
        {
          "item": "26",
          "type": "delete"
        },
        {
          "item": "26",
          "type": "delete"
        },
        {
          "item": "26",
          "type": "delete"
        }
      ],
      "rank": "rare",
      "type": "recipe"
    },
    "62": {
      "abilities": {
        "endurance": 120
      },
      "image": "item62",
      "rank": "uncommon",
      "reflection": 2,
      "type": "armor"
    },
    "63": {
      "abilities": {
        "uses": 2
      },
      "create": [
        {
          "item": "62",
          "type": "create"
        }
      ],
      "image": "recipe",
      "materials": [
        {
          "item": "51",
          "type": "delete"
        },
        {
          "item": "51",
          "type": "delete"
        },
        {
          "item": "51",
          "type": "delete"
        },
        {
          "item": "51",
          "type": "delete"
        },
        {
          "item": "51",
          "type": "delete"
        },
        {
          "item": "51",
          "type": "delete"
        },
        {
          "item": "51",
          "type": "delete"
        },
        {
          "item": "51",
          "type": "delete"
        },
        {
          "item": "51",
          "type": "delete"
        },
        {
          "item": "51",
          "type": "delete"
        },
        {
          "item": "51",
          "type": "delete"
        },
        {
          "item": "51",
          "type": "delete"
        },
        {
          "item": "51",
          "type": "delete"
        },
        {
          "item": "51",
          "type": "delete"
        },
        {
          "item": "51",
          "type": "delete"
        }
      ],
      "rank": "uncommon",
      "type": "recipe"
    },
    "64": {
      "abilities": {
        "endurance": 20
      },
      "class": "near",
      "damage": {
        "max": 1,
        "min": 0
      },
      "effectiv": 2,
      "image": "item64",
      "rank": "uncommon",
      "type": "weapon"
    },
    "65": {
      "abilities": {
        "uses": 2
      },
      "create": [
        {
          "item": "64",
          "type": "create"
        }
      ],
      "image": "recipe",
      "materials": [
        {
          "item": "51",
          "type": "delete"
        },
        {
          "item": "51",
          "type": "delete"
        },
        {
          "item": "51",
          "type": "delete"
        },
        {
          "item": "51",
          "type": "delete"
        },
        {
          "item": "51",
          "type": "delete"
        },
        {
          "item": "51",
          "type": "delete"
        },
        {
          "item": "51",
          "type": "delete"
        }
      ],
      "rank": "uncommon",
      "type": "recipe"
    },
    "66": {
      "image": "item66",
      "rank": "mythical",
      "time": "forever",
      "type": "freezing"
    },
    "67": {
      "image": "item67",
      "rank": "mythical",
      "type": "defrosting"
    },
    "68": {
      "+energy": 5,
      "act": 10,
      "class": "ALL",
      "image": "item68",
      "rank": "common",
      "type": "eat"
    },
    "69": {
      "+energy": 2,
      "+mood": 5,
      "abilities": {
        "uses": 10
      },
      "act": 3,
      "class": "ALL",
      "image": "item69",
      "rank": "uncommon",
      "type": "eat"
    },
    "70": {
      "abilities": {
        "uses": 5
      },
      "create": [
        {
          "item": "69",
          "type": "create"
        }
      ],
      "image": "recipe",
      "materials": [
        {
          "item": "68",
          "type": "delete"
        },
        {
          "item": "68",
          "type": "delete"
        }
      ],
      "rank": "uncommon",
      "type": "recipe"
    },
    "71": {
      "act": 10,
      "class": "Herbivore",
      "image": "item71",
      "rank": "common",
      "type": "eat"
    },
    "72": {
      "+mood": 25,
      "act": 20,
      "class": "ALL",
      "image": "item72",
      "rank": "uncommon",
      "type": "eat"
    },
    "73": {
      "abilities": {
        "uses": 5
      },
      "create": [
        {
          "item": "72",
          "type": "create"
        }
      ],
      "image": "recipe",
      "materials": [
        {
          "act": 5,
          "item": "31",
          "type": "endurance"
        },
        {
          "item": "71",
          "type": "delete"
        },
        {
          "item": "71",
          "type": "delete"
        }
      ],
      "rank": "uncommon",
      "type": "recipe"
    },
    "74": {
      "+mood": 20,
      "act": 10,
      "class": "ALL",
      "image": "item74",
      "rank": "uncommon",
      "type": "eat"
    },
    "75": {
      "abilities": {
        "uses": 10
      },
      "create": [
        {
          "item": "74",
          "type": "create"
        }
      ],
      "image": "recipe",
      "materials": [
        {
          "item": "11",
          "type": "delete"
        }
      ],
      "rank": "uncommon",
      "type": "recipe"
    },
    "76": {
      "-hp": 2,
      "act": 5,
      "class": "Herbivore",
      "image": "item76",
      "rank": "common",
      "type": "eat"
    },
    "77": {
      "act": 50,
      "class": "Carnivore",
      "image": "item77",
      "rank": "rare",
      "type": "eat"
    },
    "78": {
      "abilities": {
        "uses": 5
      },
      "create": [
        {
          "item": "77",
          "type": "create"
        }
      ],
      "image": "recipe",
      "materials": [
        {
          "act": 10,
          "item": "31",
          "type": "endurance"
        },
        {
          "item": "8",
          "type": "delete"
        },
        {
          "item": "9",
          "type": "delete"
        },
        {
          "item": "76",
          "type": "delete"
        }
      ],
      "rank": "rare",
      "type": "recipe"
    },
    "79": {
      "act": 15,
      "class": "Herbivore",
      "image": "item79",
      "rank": "common",
      "type": "eat"
    },
    "80": {
      "act": 50,
      "class": "Flying",
      "image": "item80",
      "rank": "rare",
      "type": "eat"
    },
    "81": {
      "+energy": 30,
      "act": 5,
      "class": "ALL",
      "image": "item81",
      "rank": "rare",
      "type": "eat"
    },
    "82": {
      "+mood": 10,
      "-hp": 2,
      "act": 15,
      "class": "Herbivore",
      "image": "item82",
      "rank": "uncommon",
      "type": "eat"
    },
    "83": {
      "+hp": 10,
      "act": 50,
      "class": "ALL",
      "image": "item83",
      "rank": "rare",
      "type": "eat"
    },
    "84": {
      "abilities": {
        "uses": 5
      },
      "create": [
        {
          "item": "83",
          "type": "create"
        }
      ],
      "image": "recipe",
      "materials": [
        {
          "act": 10,
          "item": "31",
          "type": "endurance"
        },
        {
          "item": "5",
          "type": "delete"
        },
        {
          "item": "5",
          "type": "delete"
        }
      ],
      "rank": "rare",
      "type": "recipe"
    },
    "85": {
      "act": 10,
      "class": "Herbivore",
      "image": "item85",
      "rank": "common",
      "type": "eat"
    },
    "86": {
      "act": 30,
      "class": "ALL",
      "image": "item86",
      "rank": "common",
      "type": "eat"
    },
    "87": {
      "abilities": {
        "uses": 5
      },
      "create": [
        {
          "item": "86",
          "type": "create"
        }
      ],
      "image": "recipe",
      "materials": [
        {
          "item": "85",
          "type": "delete"
        },
        {
          "item": "7",
          "type": "delete"
        }
      ],
      "rank": "rare",
      "type": "recipe"
    },
    "88": {
      "+energy": 20,
      "act": 10,
      "class": "ALL",
      "image": "item88",
      "rank": "uncommon",
      "type": "eat"
    },
    "89": {
      "abilities": {
        "uses": 5
      },
      "create": [
        {
          "item": "88",
          "type": "create"
        }
      ],
      "image": "recipe",
      "materials": [
        {
          "item": "68",
          "type": "delete"
        },
        {
          "item": "68",
          "type": "delete"
        }
      ],
      "rank": "uncommon",
      "type": "recipe"
    },
    "90": {
      "+mood": 100,
      "abilities": {
        "uses": 6
      },
      "act": 40,
      "class": "ALL",
      "image": "item90",
      "rank": "mystical",
      "type": "eat"
    },
    "91": {
      "abilities": {
        "uses": 2
      },
      "create": [
        {
          "item": "90",
          "type": "create"
        }
      ],
      "image": "recipe",
      "materials": [
        {
          "item": "68",
          "type": "delete"
        },
        {
          "item": "68",
          "type": "delete"
        },
        {
          "item": "68",
          "type": "delete"
        },
        {
          "item": "68",
          "type": "delete"
        },
        {
          "item": "11",
          "type": "delete"
        },
        {
          "item": "11",
          "type": "delete"
        },
        {
          "item": "11",
          "type": "delete"
        },
        {
          "item": "11",
          "type": "delete"
        },
        {
          "item": "11",
          "type": "delete"
        },
        {
          "item": "1",
          "type": "delete"
        },
        {
          "item": "2",
          "type": "delete"
        },
        {
          "item": "2",
          "type": "delete"
        }
      ],
      "rank": "mystical",
      "type": "recipe"
    },
    "92": {
      "act": 50,
      "class": "ALL",
      "image": "item92",
      "rank": "rare",
      "type": "eat"
    },
    "93": {
      "abilities": {
        "uses": 5
      },
      "create": [
        {
          "item": "92",
          "type": "create"
        }
      ],
      "image": "recipe",
      "materials": [
        {
          "item": "85",
          "type": "delete"
        },
        {
          "item": "85",
          "type": "delete"
        },
        {
          "item": "76",
          "type": "delete"
        },
        {
          "item": "76",
          "type": "delete"
        }
      ],
      "rank": "rare",
      "type": "recipe"
    },
    "94": {
      "+mood": 15,
      "act": 20,
      "class": "ALL",
      "image": "item94",
      "rank": "rare",
      "type": "eat"
    },
    "95": {
      "act": 10,
      "class": "Herbivore",
      "image": "item95",
      "rank": "common",
      "type": "eat"
    },
    "96": {
      "act": 30,
      "class": "ALL",
      "image": "item96",
      "rank": "uncommon",
      "type": "eat"
    },
    "97": {
      "abilities": {
        "uses": 10
      },
      "create": [
        {
          "item": "96",
          "type": "create"
        }
      ],
      "image": "recipe",
      "materials": [
        {
          "item": "95",
          "type": "delete"
        },
        {
          "item": "95",
          "type": "delete"
        }
      ],
      "rank": "uncommon",
      "type": "recipe"
    },
    "98": {
      "+mood": 20,
      "act": 50,
      "class": "Herbivore",
      "image": "item98",
      "rank": "uncommon",
      "type": "eat"
    },
    "99": {
      "+energy": 10,
      "act": 60,
      "class": "Flying",
      "image": "item99",
      "rank": "uncommon",
      "type": "eat"
    },
    "100": {
      "+hp": 10,
      "act": 60,
      "class": "Carnivore",
      "image": "item100",
      "rank": "uncommon",
      "type": "eat"
    },
    "101": {
      "abilities": {
        "uses": 5
      },
      "create": [
        {
          "item": "98",
          "type": "create"
        }
      ],
      "image": "recipe",
      "materials": [
        {
          "item": "95",
          "type": "delete"
        },
        {
          "item": "95",
          "type": "delete"
        },
        {
          "item": "11",
          "type": "delete"
        },
        {
          "item": "11",
          "type": "delete"
        }
      ],
      "rank": "uncommon",
      "type": "recipe"
    },
    "102": {
      "abilities": {
        "uses": 5
      },
      "create": [
        {
          "item": "99",
          "type": "create"
        }
      ],
      "image": "recipe",
      "materials": [
        {
          "item": "95",
          "type": "delete"
        },
        {
          "item": "95",
          "type": "delete"
        },
        {
          "item": "7",
          "type": "delete"
        },
        {
          "item": "7",
          "type": "delete"
        }
      ],
      "rank": "uncommon",
      "type": "recipe"
    },
    "103": {
      "abilities": {
        "uses": 5
      },
      "create": [
        {
          "item": "100",
          "type": "create"
        }
      ],
      "image": "recipe",
      "materials": [
        {
          "item": "95",
          "type": "delete"
        },
        {
          "item": "95",
          "type": "delete"
        },
        {
          "item": "8",
          "type": "delete"
        },
        {
          "item": "8",
          "type": "delete"
        }
      ],
      "rank": "uncommon",
      "type": "recipe"
    },
    "104": {
      "act": 30,
      "class": "Carnivore",
      "image": "item104",
      "rank": "uncommon",
      "type": "eat"
    },
    "105": {
      "abilities": {
        "uses": 10
      },
      "create": [
        {
          "item": "104",
          "type": "create"
        }
      ],
      "image": "recipe",
      "materials": [
        {
          "act": 10,
          "item": "31",
          "type": "endurance"
        },
        {
          "item": "5",
          "type": "delete"
        }
      ],
      "rank": "uncommon",
      "type": "recipe"
    },
    "106": {
      "+hp": 20,
      "+mood": 20,
      "abilities": {
        "uses": 2
      },
      "act": 100,
      "class": "Carnivore",
      "image": "item106",
      "rank": "mystical",
      "type": "eat"
    },
    "107": {
      "abilities": {
        "uses": 2
      },
      "create": [
        {
          "item": "106",
          "type": "create"
        }
      ],
      "image": "recipe",
      "materials": [
        {
          "item": "38",
          "type": "delete"
        },
        {
          "item": "86",
          "type": "delete"
        },
        {
          "item": "40",
          "type": "delete"
        }
      ],
      "rank": "mystical",
      "type": "recipe"
    },
    "108": {
      "act": 50,
      "class": "ALL",
      "image": "item108",
      "rank": "rare",
      "type": "eat"
    },
    "109": {
      "abilities": {
        "uses": 5
      },
      "create": [
        {
          "item": "108",
          "type": "create"
        }
      ],
      "image": "recipe",
      "materials": [
        {
          "item": "96",
          "type": "delete"
        },
        {
          "item": "8",
          "type": "delete"
        },
        {
          "item": "9",
          "type": "delete"
        }
      ],
      "rank": "rare",
      "type": "recipe"
    },
    "110": {
      "col_repit": {
        "act": 4,
        "type": "static"
      },
      "drop_items": [
        {
          "abilities": {},
          "chance": [
            2,
            10
          ],
          "col": {
            "max": 4,
            "min": 1,
            "type": "random"
          },
          "id": "38"
        },
        {
          "abilities": {},
          "chance": [
            2,
            10
          ],
          "col": {
            "max": 4,
            "min": 1,
            "type": "random"
          },
          "id": "40"
        },
        {
          "abilities": {},
          "chance": [
            2,
            10
          ],
          "col": {
            "max": 4,
            "min": 1,
            "type": "random"
          },
          "id": "42"
        },
        {
          "abilities": {},
          "chance": [
            2,
            10
          ],
          "col": {
            "max": 4,
            "min": 1,
            "type": "random"
          },
          "id": "48"
        },
        {
          "abilities": {},
          "chance": [
            2,
            10
          ],
          "col": {
            "max": 2,
            "min": 1,
            "type": "random"
          },
          "id": "50"
        },
        {
          "abilities": {},
          "chance": [
            2,
            10
          ],
          "col": {
            "max": 10,
            "min": 1,
            "type": "random"
          },
          "id": "68"
        },
        {
          "abilities": {},
          "chance": [
            2,
            10
          ],
          "col": {
            "max": 4,
            "min": 1,
            "type": "random"
          },
          "id": "69"
        },
        {
          "abilities": {},
          "chance": [
            2,
            10
          ],
          "col": {
            "max": 4,
            "min": 1,
            "type": "random"
          },
          "id": "72"
        },
        {
          "abilities": {},
          "chance": [
            2,
            10
          ],
          "col": {
            "max": 4,
            "min": 1,
            "type": "random"
          },
          "id": "74"
        },
        {
          "abilities": {},
          "chance": [
            2,
            10
          ],
          "col": {
            "max": 4,
            "min": 1,
            "type": "random"
          },
          "id": "77"
        },
        {
          "abilities": {},
          "chance": [
            2,
            10
          ],
          "col": {
            "max": 20,
            "min": 5,
            "type": "random"
          },
          "id": "79"
        },
        {
          "abilities": {},
          "chance": [
            2,
            10
          ],
          "col": {
            "max": 10,
            "min": 2,
            "type": "random"
          },
          "id": "80"
        },
        {
          "abilities": {},
          "chance": [
            2,
            10
          ],
          "col": {
            "max": 4,
            "min": 1,
            "type": "random"
          },
          "id": "81"
        },
        {
          "abilities": {},
          "chance": [
            2,
            10
          ],
          "col": {
            "max": 4,
            "min": 1,
            "type": "random"
          },
          "id": "83"
        },
        {
          "abilities": {},
          "chance": [
            2,
            10
          ],
          "col": {
            "max": 10,
            "min": 5,
            "type": "random"
          },
          "id": "85"
        },
        {
          "abilities": {},
          "chance": [
            4,
            10
          ],
          "col": {
            "max": 5,
            "min": 2,
            "type": "random"
          },
          "id": "86"
        },
        {
          "abilities": {},
          "chance": [
            2,
            10
          ],
          "col": {
            "max": 4,
            "min": 1,
            "type": "random"
          },
          "id": "88"
        },
        {
          "abilities": {},
          "chance": [
            1,
            10
          ],
          "col": {
            "act": 1,
            "type": "static"
          },
          "id": "90"
        },
        {
          "abilities": {},
          "chance": [
            2,
            10
          ],
          "col": {
            "max": 4,
            "min": 1,
            "type": "random"
          },
          "id": "92"
        },
        {
          "abilities": {},
          "chance": [
            2,
            10
          ],
          "col": {
            "max": 5,
            "min": 2,
            "type": "random"
          },
          "id": "94"
        },
        {
          "abilities": {},
          "chance": [
            5,
            100
          ],
          "col": {
            "max": 30,
            "min": 10,
            "type": "random"
          },
          "id": "95"
        },
        {
          "abilities": {},
          "chance": [
            1,
            10
          ],
          "col": {
            "max": 6,
            "min": 2,
            "type": "random"
          },
          "id": "96"
        },
        {
          "abilities": {},
          "chance": [
            2,
            10
          ],
          "col": {
            "max": 4,
            "min": 1,
            "type": "random"
          },
          "id": "98"
        },
        {
          "abilities": {},
          "chance": [
            2,
            10
          ],
          "col": {
            "max": 4,
            "min": 1,
            "type": "random"
          },
          "id": "99"
        },
        {
          "abilities": {},
          "chance": [
            2,
            10
          ],
          "col": {
            "max": 4,
            "min": 1,
            "type": "random"
          },
          "id": "100"
        },
        {
          "abilities": {},
          "chance": [
            2,
            10
          ],
          "col": {
            "max": 10,
            "min": 4,
            "type": "random"
          },
          "id": "104"
        },
        {
          "abilities": {},
          "chance": [
            3,
            10
          ],
          "col": {
            "max": 4,
            "min": 1,
            "type": "random"
          },
          "id": "106"
        },
        {
          "abilities": {},
          "chance": [
            4,
            10
          ],
          "col": {
            "max": 10,
            "min": 2,
            "type": "random"
          },
          "id": "108"
        }
      ],
      "image": "case",
      "rank": "mythical",
      "type": "case"
    },
    "111": {
      "col_repit": {
        "act": 4,
        "type": "static"
      },
      "drop_items": [
        {
          "abilities": {},
          "chance": [
            2,
            10
          ],
          "col": {
            "act": 1,
            "type": "static"
          },
          "id": "30"
        },
        {
          "abilities": {},
          "chance": [
            2,
            10
          ],
          "col": {
            "act": 1,
            "type": "static"
          },
          "id": "32"
        },
        {
          "abilities": {},
          "chance": [
            3,
            10
          ],
          "col": {
            "act": 1,
            "type": "static"
          },
          "id": "34"
        },
        {
          "abilities": {},
          "chance": [
            3,
            10
          ],
          "col": {
            "act": 1,
            "type": "static"
          },
          "id": "37"
        },
        {
          "abilities": {},
          "chance": [
            2,
            10
          ],
          "col": {
            "act": 1,
            "type": "static"
          },
          "id": "39"
        },
        {
          "abilities": {},
          "chance": [
            2,
            10
          ],
          "col": {
            "max": 4,
            "min": 2,
            "type": "random"
          },
          "id": "40"
        },
        {
          "abilities": {},
          "chance": [
            2,
            10
          ],
          "col": {
            "max": 4,
            "min": 2,
            "type": "random"
          },
          "id": "43"
        },
        {
          "abilities": {},
          "chance": [
            4,
            10
          ],
          "col": {
            "act": 1,
            "type": "static"
          },
          "id": "46"
        },
        {
          "abilities": {},
          "chance": [
            4,
            10
          ],
          "col": {
            "act": 1,
            "type": "static"
          },
          "id": "56"
        },
        {
          "abilities": {},
          "chance": [
            4,
            10
          ],
          "col": {
            "max": 4,
            "min": 2,
            "type": "random"
          },
          "id": "70"
        },
        {
          "abilities": {},
          "chance": [
            4,
            10
          ],
          "col": {
            "max": 4,
            "min": 2,
            "type": "random"
          },
          "id": "73"
        },
        {
          "abilities": {},
          "chance": [
            4,
            10
          ],
          "col": {
            "max": 4,
            "min": 2,
            "type": "random"
          },
          "id": "75"
        },
        {
          "abilities": {},
          "chance": [
            4,
            10
          ],
          "col": {
            "max": 4,
            "min": 2,
            "type": "random"
          },
          "id": "78"
        },
        {
          "abilities": {},
          "chance": [
            4,
            10
          ],
          "col": {
            "max": 4,
            "min": 2,
            "type": "random"
          },
          "id": "84"
        },
        {
          "abilities": {},
          "chance": [
            4,
            10
          ],
          "col": {
            "max": 4,
            "min": 2,
            "type": "random"
          },
          "id": "87"
        },
        {
          "abilities": {},
          "chance": [
            4,
            10
          ],
          "col": {
            "max": 4,
            "min": 2,
            "type": "random"
          },
          "id": "89"
        },
        {
          "abilities": {},
          "chance": [
            4,
            10
          ],
          "col": {
            "max": 3,
            "min": 1,
            "type": "random"
          },
          "id": "91"
        },
        {
          "abilities": {},
          "chance": [
            4,
            10
          ],
          "col": {
            "max": 4,
            "min": 2,
            "type": "random"
          },
          "id": "93"
        },
        {
          "abilities": {},
          "chance": [
            3,
            10
          ],
          "col": {
            "max": 4,
            "min": 2,
            "type": "random"
          },
          "id": "97"
        },
        {
          "abilities": {},
          "chance": [
            4,
            10
          ],
          "col": {
            "max": 4,
            "min": 2,
            "type": "random"
          },
          "id": "101"
        },
        {
          "abilities": {},
          "chance": [
            4,
            10
          ],
          "col": {
            "max": 4,
            "min": 2,
            "type": "random"
          },
          "id": "102"
        },
        {
          "abilities": {},
          "chance": [
            4,
            10
          ],
          "col": {
            "max": 4,
            "min": 2,
            "type": "random"
          },
          "id": "103"
        },
        {
          "abilities": {},
          "chance": [
            4,
            10
          ],
          "col": {
            "max": 4,
            "min": 2,
            "type": "random"
          },
          "id": "105"
        },
        {
          "abilities": {},
          "chance": [
            4,
            10
          ],
          "col": {
            "max": 4,
            "min": 2,
            "type": "random"
          },
          "id": "107"
        },
        {
          "abilities": {},
          "chance": [
            4,
            10
          ],
          "col": {
            "max": 4,
            "min": 2,
            "type": "random"
          },
          "id": "109"
        }
      ],
      "image": "case",
      "rank": "mythical",
      "type": "case"
    },
    "112": {
      "col_repit": {
        "act": 1,
        "type": "static"
      },
      "drop_items": [
        {
          "abilities": {},
          "chance": [
            1,
            100
          ],
          "col": {
            "act": 1,
            "type": "static"
          },
          "id": "23"
        },
        {
          "abilities": {},
          "chance": [
            1,
            1000
          ],
          "col": {
            "act": 1,
            "type": "static"
          },
          "id": "24"
        },
        {
          "abilities": {},
          "chance": [
            2,
            10
          ],
          "col": {
            "act": 1,
            "type": "static"
          },
          "id": "110"
        },
        {
          "abilities": {},
          "chance": [
            2,
            10
          ],
          "col": {
            "act": 1,
            "type": "static"
          },
          "id": "111"
        }
      ],
      "image": "case",
      "rank": "mythical",
      "type": "case"
    }
  }